jobQuery/__init__.py
jobQuery/jobAPI.py
jobQuery-2.0.2.dist-info/METADATA
jobQuery-2.0.2.dist-info/WHEEL
jobQuery-2.0.2.dist-info/top_level.txt
jobQuery-2.0.2.dist-info/RECORD
